fheom/__init__.py
fheom/fheom.py
fheom/fmo.py
fheom/heom_utils.py
fheom-1.0.1.dist-info/licenses/LICENSE
fheom-1.0.1.dist-info/METADATA
fheom-1.0.1.dist-info/WHEEL
fheom-1.0.1.dist-info/top_level.txt
fheom-1.0.1.dist-info/RECORD
