Metadata-Version: 2.4
Name: fHEOM
Version: 1.0.1
Summary: Low-rank factorization for efficient HEOM simulations of quantum coherence in biological systems
Home-page: https://github.com/rihp/fHEOM
Author: Roberto Ignacio Henriquez-Perozo
Author-email: Roberto Ignacio Henriquez-Perozo <roberto@henriquezperozo.com>
License-Expression: MIT
Project-URL: Homepage, https://github.com/rihp/fHEOM
Project-URL: Repository, https://github.com/rihp/fHEOM
Keywords: quantum biology,HEOM,FMO complex,open quantum systems,low-rank factorization
Classifier: Development Status :: 4 - Beta
Classifier: Intended Audience :: Science/Research
Classifier: Topic :: Scientific/Engineering :: Physics
Classifier: Programming Language :: Python :: 3
Classifier: Programming Language :: Python :: 3.8
Classifier: Programming Language :: Python :: 3.9
Classifier: Programming Language :: Python :: 3.10
Classifier: Programming Language :: Python :: 3.11
Classifier: Programming Language :: Python :: 3.12
Classifier: Operating System :: OS Independent
Requires-Python: >=3.8
License-File: LICENSE
Requires-Dist: qutip>=5.2.0
Requires-Dist: numpy>=1.24.0
Requires-Dist: scipy>=1.10.0
Requires-Dist: matplotlib>=3.7.0
Requires-Dist: seaborn>=0.12.0
Requires-Dist: pandas>=2.0.0
Requires-Dist: tqdm>=4.65.0
Provides-Extra: gpu
Requires-Dist: cupy-cuda12x>=13.0.0; extra == "gpu"
Provides-Extra: dev
Requires-Dist: pytest>=7.3.0; extra == "dev"
Requires-Dist: black>=23.0.0; extra == "dev"
Requires-Dist: flake8>=6.0.0; extra == "dev"
Dynamic: author
Dynamic: home-page
Dynamic: license-file
Dynamic: requires-python
